[{"user":"x","line1":"Maths","line2":"English","line3":"Science","line4":"History","line5":"Music"},{"user":"johnny","line1":"English","line2":"History","line3":"Music","line4":"Geography","line5":"Maths"},{"user":"polivebibson","line1":"Music","line2":"English","line3":"Maths","line4":"Science","line5":"Geography"},{"user":"yujin","line1":"Maths","line2":"English","line3":"Maths","line4":"Geography","line5":"Science"},{"user":"yujin","line1":"Maths","line2":"English","line3":"Geography","line4":"Science","line5":"Art"},{"user":"yaya","line1":"Maths","line2":"English","line3":"Art","line4":"Music","line5":"Geography"},{"user":"test","line1":"Science","line2":"Art","line3":"Maths","line4":"Maths","line5":"Geography"},{"user":"test","line1":"Science","line2":"Maths","line3":"English","line4":"Geography","line5":"Art"},{"user":"snoopy","line1":"Maths","line2":"English","line3":"Geography","line4":"History","line5":"History"},{"user":"snoopy","line1":"History","line2":"Science","line3":"English","line4":"Maths","line5":"Music"},{"user":"arthur","line1":"English","line2":"Geography","line3":"Maths","line4":"Science","line5":"Science"},{"user":"arthur","line1":"English","line2":"Maths","line3":"Science","line4":"Geography","line5":"Art"}]